bike/__init__.py
bike/controllers.py
bike/fields.py
bike/models.py
bike-0.3.6.dist-info/LICENSE
bike-0.3.6.dist-info/METADATA
bike-0.3.6.dist-info/WHEEL
bike-0.3.6.dist-info/RECORD
