Metadata-Version: 2.1
Name: bike
Version: 0.3.6
Summary: A lightweight model validator for modern projects.
Home-page: https://github.com/manasseslima/bike
License: MIT
Author: Manasses Lima
Author-email: manasseslima@gmail.com
Requires-Python: >=3.10,<4.0
Classifier: License :: OSI Approved :: MIT License
Classifier: Programming Language :: Python :: 3
Classifier: Programming Language :: Python :: 3.10
Classifier: Programming Language :: Python :: 3.11
Project-URL: Repository, https://github.com/manasseslima/bike
